fastcoref/__init__.py
fastcoref/f_coref.py
fastcoref/coref_models/__init__.py
fastcoref/coref_models/modeling_fcoref.py
fastcoref/coref_models/modeling_lingmess.py
fastcoref/utilities/__init__.py
fastcoref/utilities/collate.py
fastcoref/utilities/consts.py
fastcoref/utilities/coref_dataset.py
fastcoref/utilities/util.py
fastcoref-1.7.1.dist-info/LICENSE
fastcoref-1.7.1.dist-info/METADATA
fastcoref-1.7.1.dist-info/WHEEL
fastcoref-1.7.1.dist-info/top_level.txt
fastcoref-1.7.1.dist-info/RECORD
