Metadata-Version: 2.1
Name: fastcoref
Version: 1.7.1
Summary: UNKNOWN
Home-page: https://github.com/shon-otmazgin/fastcoref
Author: Shon Otmazgin, Arie Cattan, Yoav Goldberg
Author-email: shon711@gmail.com
License: MIT
Platform: UNKNOWN
License-File: LICENSE
Requires-Dist: tqdm (>=4.64.0)
Requires-Dist: numpy (>=1.21.6)
Requires-Dist: scipy (>=1.7.3)
Requires-Dist: spacy (>=3.0.6)
Requires-Dist: torch (>=1.10.0)
Requires-Dist: transformers (>=4.11.3)
Requires-Dist: datasets (>=2.1.0)
